patho_pix-0.1.1.dist-info/METADATA
patho_pix-0.1.1.dist-info/WHEEL
patho_pix-0.1.1.dist-info/licenses/LICENCE.md
patho_pix/__init__.py
patho_pix/io.py
patho_pix/main.py
patho_pix/normalization.py
patho_pix/tiling.py
patho_pix/utils/__init__.py
patho_pix/utils/custom_tiler.py
patho_pix/utils/jpeg_to_tiff.py
patho_pix-0.1.1.dist-info/RECORD
