Metadata-Version: 2.1
Name: patho-pix
Version: 0.1.1
Summary: Preprocessing framework for pathological images
License: MIT
Requires-Python: <=3.11,>=3.8
Requires-Dist: histolab>=0.7.0
Requires-Dist: large-image>=1.28.2
Requires-Dist: openslide-python>=1.3.1
Requires-Dist: pillow>=10.3.0
Requires-Dist: large-image-source-vips>=1.28.2
Requires-Dist: large-image-source-multi>=1.28.2
Requires-Dist: large-image-source-openjpeg>=1.28.2
Requires-Dist: pandas>=2.0.3
Requires-Dist: numpy>=1.24.4
Requires-Dist: opencv-python>=4.9.0.80
Requires-Dist: torch>=2.3.0
Requires-Dist: torchvision>=0.18.0
